zp_pycrc/__init__.py
zp_pycrc-0.0.1.dist-info/METADATA
zp_pycrc-0.0.1.dist-info/WHEEL
zp_pycrc-0.0.1.dist-info/top_level.txt
zp_pycrc-0.0.1.dist-info/RECORD
